veripupil/__init__.py
veripupil/hyperparameters.py
veripupil/hyperparameters_test.py
veripupil/trainer.py
veripupil-0.0.11.dist-info/LICENSE.txt
veripupil-0.0.11.dist-info/METADATA
veripupil-0.0.11.dist-info/RECORD
veripupil-0.0.11.dist-info/WHEEL
veripupil-0.0.11.dist-info/top_level.txt
