Metadata-Version: 2.1
Name: veripupil
Version: 0.0.11
Summary: Python classes for optimizing models against veri
Home-page: http://github.com/bgokden/modeloptimizer
Author: Berk Gokden
Author-email: berkgokden@gmail.com
License: MIT
Keywords: veri service python client ml keras tensorflow
Platform: UNKNOWN
Requires-Dist: veriservice
Requires-Dist: keras
Requires-Dist: tensorflow
